skreep/__init__.py
skreep/datasheet.py
skreep/display.py
skreep/download.py
skreep/save.py
skreep/skreep.py
skreep-0.1.5.dist-info/LICENSE
skreep-0.1.5.dist-info/METADATA
skreep-0.1.5.dist-info/WHEEL
skreep-0.1.5.dist-info/top_level.txt
skreep-0.1.5.dist-info/RECORD
