Metadata-Version: 2.1
Name: skreep
Version: 0.1.5
Summary: Data scraper
Home-page: https://github.com/khorud/Skreep
Author: Korud
Author-email: khorud@yahoo.com
License: UNKNOWN
Platform: UNKNOWN
Classifier: Programming Language :: Python :: 3
Classifier: Programming Language :: Python :: 3.7
Classifier: License :: OSI Approved :: GNU General Public License v3 (GPLv3)
Classifier: Operating System :: OS Independent
Requires-Python: >=3
Requires-Dist: selenium
